Workbook

Sheet README
A1: AYE SI CENA - COSTED FUSION MATRIX
A3: What this is | B3: 150 dishes: Scottish-led (77), with English, Greek, Nordic, Basque and disputed-origin entries, plus a 22-dish Peruvian-base block where the fusion runs the other way - a Peruvian dish with the Scottish or European swap made on top of it.
A5: READ THIS FIRST | B5: Every figure in 'Est. food cost (S/)' is an ESTIMATE produced without a market run.
B6: They are order-of-magnitude only and MUST be replaced with real prices before you quote a client.
B7: Prices are PEN, per portion, Lima 2026. 'Cost verified?' is 'No' on every row until you fix that.
A9: How to use it | B9: 1. Do one market run. Record what you actually paid.
B10: 2. Overwrite the blue cost cells. Set 'Cost verified?' to Yes.
B11: 3. Watch the Food cost % column: target 25-30%. Red above 32%.
B12: 4. Check the Mix Check tab - it enforces the Scottish-led ratio.
A14: Editable cells | B14: Blue text = your inputs (cost, price). Black = formulas. Do not overwrite formulas.
A16: Service format | B16: Drop-off = survives a van. Buffet = holds on a hot line. Plated = needs a brigade.
B17: Live station = you cook it in front of the guest. Never sell a Live station dish as drop-off.
A19: Not included | B19: Drinks. 115 of these 130 dishes are sellable before the giro especial clears;
B20: the 15 flagged 'Needs liquor licence' are not. Filter on that column before publishing a menu.
A22: Annual fixtures | B22: Burns Night 25 Jan (haggis, neeps, tatties, cranachan, clootie dumpling).
B23: Hogmanay 31 Dec (black bun, steak pie). St Andrew's Day 30 Nov.
B24: These are bookable products with fixed menus, not menu items.

Sheet Matrix
A1: ID | B1: Dish | C1: Origin dish | D1: Sub-origin | E1: Category | F1: Peruvian fusion | G1: Service format | H1: Needs liquor licence | I1: Veg | J1: Key local ingredients | K1: Primary Lima source | L1: Est. food cost (S/) | M1: Suggested price (S/) | N1: Food cost % | O1: Cost verified? | P1: Action
A2: 1 | B2: Haggis Bonbons | C2: Haggis | D2: Scottish | E2: Canape | F2: Crumbed and fried; aji panca in the breadcrumb, huacatay aioli. Offal is familiar to Peruvian palates - this is the least intimidating way in. | G2: Drop-off | H2: No | I2: No | J2: Lamb offal, oats, aji panca, huacatay | K2: Mercado de Magdalena (offal); Makro (oats) | L2: 2.2 | M2: 8 | N2: =IFERROR(L2/M2,"") | O2: No - estimate | P2: =IF(N2="","",IF(N2>0.32,"Reprice or resource",IF(N2<0.2,"Check cost is realistic","OK")))
A3: 2 | B3: Morcilla & Apple Empanadas | C3: Black pudding | D3: Scottish | E3: Canape | F3: Peruvian empanada dough around morcilla reworked with oats, mace and white pepper; rocoto-apple chutney. | G3: Drop-off | H3: No | I3: No | J3: Artisanal morcilla, rocoto, manzana israel | K3: Artisanal butcher, Surquillo N.1 | L3: 2.5 | M3: 9 | N3: =IFERROR(L3/M3,"") | O3: No - estimate | P3: =IF(N3="","",IF(N3>0.32,"Reprice or resource",IF(N3<0.2,"Check cost is realistic","OK")))
A4: 3 | B4: Smoked Trout Oatcakes | C4: Oatcakes with smoked fish | D4: Scottish | E4: Canape | F4: Highland oatcake topped with Andean smoked trout and a crowdie-style fresh cheese. | G4: Drop-off | H4: No | I4: No | J4: Trucha andina, queso fresco | K4: Terminal Pesquero VMT; Surquillo N.1 | L4: 3 | M4: 10 | N4: =IFERROR(L4/M4,"") | O4: No - estimate | P4: =IF(N4="","",IF(N4>0.32,"Reprice or resource",IF(N4<0.2,"Check cost is realistic","OK")))
A5: 4 | B5: Mini Forfar Bridies | C5: Forfar bridie | D5: Scottish | E5: Canape | F5: Shortcrust hand pie; local beef mince lifted with aji amarillo and native onion. | G5: Drop-off | H5: No | I5: No | J5: Beef mince, aji amarillo, cebolla roja | K5: Oregon Foods; Surquillo N.1 | L5: 3.2 | M5: 11 | N5: =IFERROR(L5/M5,"") | O5: No - estimate | P5: =IF(N5="","",IF(N5>0.32,"Reprice or resource",IF(N5<0.2,"Check cost is realistic","OK")))
A6: 5 | B6: Scotch Pie Minis | C6: Scotch pie | D6: Scottish | E6: Canape | F6: Hot-water crust filled with spiced cordero and aji panca instead of mace-only mutton. | G6: Drop-off | H6: No | I6: No | J6: Cordero, aji panca, comino | K6: Mercado de Magdalena | L6: 3 | M6: 11 | N6: =IFERROR(L6/M6,"") | O6: No - estimate | P6: =IF(N6="","",IF(N6>0.32,"Reprice or resource",IF(N6<0.2,"Check cost is realistic","OK")))
A7: 6 | B7: Haggis Sausage Rolls | C7: Sausage roll | D7: Scottish | E7: Canape | F7: Puff pastry, haggis-spiced filling, glazed with a chancaca brown sauce. | G7: Drop-off | H7: No | I7: No | J7: Lamb, oats, chancaca | K7: Mercado de Magdalena; Surquillo N.1 | L7: 2.6 | M7: 9 | N7: =IFERROR(L7/M7,"") | O7: No - estimate | P7: =IF(N7="","",IF(N7>0.32,"Reprice or resource",IF(N7<0.2,"Check cost is realistic","OK")))
A8: 7 | B8: Cullen Skink Croquettes | C8: Cullen skink | D8: Scottish | E8: Canape | F8: The No.1-ranked Scottish dish as a bite: smoked paiche and native yellow potato, crumbed. | G8: Drop-off | H8: No | I8: No | J8: Paiche ahumado, papa amarilla | K8: Terminal Pesquero VMT | L8: 3.4 | M8: 12 | N8: =IFERROR(L8/M8,"") | O8: No - estimate | P8: =IF(N8="","",IF(N8>0.32,"Reprice or resource",IF(N8<0.2,"Check cost is realistic","OK")))
A9: 8 | B9: Lorne Sausage Sliders | C9: Lorne (square) sausage | D9: Scottish | E9: Canape | F9: Square sausage in a mini pan francés with salsa criolla in place of brown sauce. | G9: Drop-off | H9: No | I9: No | J9: Beef/pork mince, cebolla, limon | K9: Makro; local bakery | L9: 3 | M9: 10 | N9: =IFERROR(L9/M9,"") | O9: No - estimate | P9: =IF(N9="","",IF(N9>0.32,"Reprice or resource",IF(N9<0.2,"Check cost is realistic","OK")))
A10: 9 | B10: Tattie Scone & Black Pudding Bites | C10: Tattie scone | D10: Scottish | E10: Canape | F10: Griddled native-yellow-potato scone as the base, morcilla and a quail egg on top. | G10: Live station | H10: No | I10: No | J10: Papa amarilla, morcilla, huevo de codorniz | K10: Surquillo N.1; artisanal butcher | L10: 2.8 | M10: 10 | N10: =IFERROR(L10/M10,"") | O10: No - estimate | P10: =IF(N10="","",IF(N10>0.32,"Reprice or resource",IF(N10<0.2,"Check cost is realistic","OK")))
A11: 10 | B11: Potted Hough Toasts | C11: Potted hough | D11: Scottish | E11: Canape | F11: Cold-set beef shin terrine on toast with aji limo pickle. Cheap cut, zero service risk. | G11: Drop-off | H11: No | I11: No | J11: Osobuco/falda, aji limo | K11: Surquillo N.1 | L11: 2.4 | M11: 9 | N11: =IFERROR(L11/M11,"") | O11: No - estimate | P11: =IF(N11="","",IF(N11>0.32,"Reprice or resource",IF(N11<0.2,"Check cost is realistic","OK")))
A12: 11 | B12: Whisky-Cured Trout Blinis | C12: Gravadlax / cured salmon | D12: Nordic | E12: Canape | F12: Trout cured in whisky, sugar and dill; aguaymanto compote to cut the fat. | G12: Drop-off | H12: Yes | I12: No | J12: Trucha, aguaymanto, eneldo | K12: Terminal Pesquero VMT; Surquillo N.1 | L12: 4 | M12: 14 | N12: =IFERROR(L12/M12,"") | O12: No - estimate | P12: =IF(N12="","",IF(N12>0.32,"Reprice or resource",IF(N12<0.2,"Check cost is realistic","OK")))
A13: 12 | B13: Crowdie & Aguaymanto Oatcakes | C13: Crowdie | D13: Scottish | E13: Canape | F13: Scotland's fresh cheese made locally from queso fresco curd; aguaymanto chutney. | G13: Drop-off | H13: No | I13: Yes | J13: Queso fresco, aguaymanto | K13: Surquillo N.1 | L13: 2.2 | M13: 8 | N13: =IFERROR(L13/M13,"") | O13: No - estimate | P13: =IF(N13="","",IF(N13>0.32,"Reprice or resource",IF(N13<0.2,"Check cost is realistic","OK")))
... A224: 223 | B224: Bizcocho de Quinua y Lucuma | C224: Bizcocho | D224: Peruvian | E224: Bakery | F224: Peruvian base, Scottish move: a quinoa-flour sponge built to the density of a Scottish tea loaf, with lucuma buttercream. It slices for a stand rather than a plate. | G224: Drop-off | H224: No | I224: Yes | J224: Quinua, lucuma, mantequilla, huevo | K224: Makro; Surquillo N.1 | L224: 2.7 | M224: 10 | N224: =IFERROR(L224/M224,"") | O224: No - estimate | P224: =IF(N224="","",IF(N224>0.32,"Reprice or resource",IF(N224<0.2,"Check cost is realistic","OK")))
B226: Portfolio average | L226: =AVERAGE(L2:L224) | M226: =AVERAGE(M2:M224) | N226: =IFERROR(L226/M226,"") | P226: =IF(N226>0.32,"Portfolio food cost too high","Portfolio food cost OK")

Sheet Mix Check
A1: MIX CHECK - enforces the Scottish-led ratio and the service-format balance
A3: Sub-origin | B3: Count | C3: Share | D3: Cap agreed | E3: Status
A4: Scottish | B4: =COUNTIF(Matrix!$D$2:$D$224,"Scottish") | C4: =IFERROR(B4/$B$13,"") | D4: 0.5 | E4: =IF(C4>=D4,"OK","Too few - cook more Scottish")
A5: Scottish (Glasgow) | B5: =COUNTIF(Matrix!$D$2:$D$224,"Scottish (Glasgow)") | C5: =IFERROR(B5/$B$13,"")
A6: English | B6: =COUNTIF(Matrix!$D$2:$D$224,"English") | C6: =IFERROR(B6/$B$13,"") | D6: 0.2 | E6: =IF(C6<=D6,"OK","Over cap - trim")
A7: Greek | B7: =COUNTIF(Matrix!$D$2:$D$224,"Greek") | C7: =IFERROR(B7/$B$13,"") | D7: 0.2 | E7: =IF(C7<=D7,"OK","Over cap - trim")
A8: Nordic | B8: =COUNTIF(Matrix!$D$2:$D$224,"Nordic") | C8: =IFERROR(B8/$B$13,"") | D8: 0.2 | E8: =IF(C8<=D8,"OK","Over cap - trim")
A9: Basque | B9: =COUNTIF(Matrix!$D$2:$D$224,"Basque") | C9: =IFERROR(B9/$B$13,"") | D9: 0.15 | E9: =IF(C9<=D9,"OK","Over cap - trim")
A10: Peruvian | B10: =COUNTIF(Matrix!$D$2:$D$224,"Peruvian") | C10: =IFERROR(B10/$B$13,"")
A11: Disputed (Lake District / Scotland) | B11: =COUNTIF(Matrix!$D$2:$D$224,"Disputed (Lake District / Scotland)") | C11: =IFERROR(B11/$B$13,"")
A13: TOTAL | B13: =SUM(B4:B11)
A15: Service format | B15: Count
A16: Drop-off | B16: =COUNTIF(Matrix!$G$2:$G$224,"Drop-off")
A17: Buffet | B17: =COUNTIF(Matrix!$G$2:$G$224,"Buffet")
A18: Plated | B18: =COUNTIF(Matrix!$G$2:$G$224,"Plated")
A19: Live station | B19: =COUNTIF(Matrix!$G$2:$G$224,"Live station")
A21: Sellable without liquor licence | B21: =COUNTIF(Matrix!$H$2:$H$224,"No")
A22: Vegetarian | B22: =COUNTIF(Matrix!$I$2:$I$224,"Yes")
A24: Costs still unverified | B24: =COUNTIF(Matrix!$O$2:$O$224,"No - estimate") | C24: Drive this to zero. Until then nothing here is quotable.

Sheet Sourcing
A1: Source | B1: What to buy there | C1: Why | D1: Verify
A2: Mercado N.1 de Surquillo | B2: Native potatoes, ajies (amarillo, panca, limo, rocoto), huacatay, muna, lucuma, chirimoya, aguaymanto, choclo, queso fresco and paria | C2: Where Lima's serious kitchens buy. Best price on everything native. | D2: Walk it once with a notebook before costing anything
A3: Terminal Pesquero VMT / Minka (Callao) | B3: Trout, paiche, corvina, chita, langostinos, oysters | C3: Wholesale pricing; early morning only | D3: Check the veda calendar - closed seasons are law, not preference
A4: Mercado de Magdalena / artisanal butcher | B4: Morcilla, lamb, offal, beef shin, pork belly | C4: Your black pudding and haggis substitutes come from here | D4: Ask them to make morcilla to your oat-and-mace spec
A5: Makro | B5: Flour, sugar, oats, quinoa, eggs, oil, bulk dry goods | C5: Bulk pricing on everything that is not native | D5: Compare unit price against Vivanda before defaulting here
A6: Oregon Foods | B6: Beef tenderloin, premium cuts, duck | C6: Only worth it for the plated tier | D6: Tenderloin price drives the whole Tier 3 margin - track it weekly
A7: Vivanda / Wong premium | B7: European butter, cream, mature cheddar | C7: Butter quality decides your shortbread. Do not economise here. | D7: Butter is your single biggest bakery cost - price it monthly
A8: Specialist importer (Gourmet Peru, Euro Food and similar) | B8: Filo pastry, imported cheese, olives, anchovies, Irn Bru | C8: They already hold the DIGESA registrations - do not import yourself | D8: Get a wholesale account; retail pricing kills these margins
A9: Local cacao distributor (Cacaosuyo, Shattell, Amazona and similar) | B9: 70% dark chocolate, cacao nibs | C9: Peruvian cacao is a selling point, not just an ingredient | D9: Bulk couverture pricing differs hugely from retail bars
A10: Local bakery partner | B10: Pan frances, brioche, sourdough | C10: Cheaper than baking bread yourself until volume justifies it | D10: Negotiate a standing daily order
